oes/__init__.py
oes-1.0.2.dist-info/LICENSE
oes-1.0.2.dist-info/METADATA
oes-1.0.2.dist-info/WHEEL
oes-1.0.2.dist-info/top_level.txt
oes-1.0.2.dist-info/RECORD
