Metadata-Version: 2.1
Name: oes
Version: 1.0.2
Summary: Optimal operation of energy storage
Home-page: https://github.com/solstice-ai/optimal-energy-storage
Author: Julian de Hoog
Author-email: julian@dehoog.ca
License: MIT
Platform: UNKNOWN
Requires-Dist: pandas
